spacy_arguing_lexicon/__init__.py
spacy_arguing_lexicon/arguments.py
spacy_arguing_lexicon/exceptions.py
spacy_arguing_lexicon/experiment.py
spacy_arguing_lexicon/parsers.py
spacy_arguing_lexicon/lexicon/en/macros/intensifiers.tff
spacy_arguing_lexicon/lexicon/en/macros/modals.tff
spacy_arguing_lexicon/lexicon/en/macros/pronoun.tff
spacy_arguing_lexicon/lexicon/en/macros/spoken.tff
spacy_arguing_lexicon/lexicon/en/macros/wordclasses.tff
spacy_arguing_lexicon/lexicon/en/patterns/assessments.tff
spacy_arguing_lexicon/lexicon/en/patterns/authority.tff
spacy_arguing_lexicon/lexicon/en/patterns/causation.tff
spacy_arguing_lexicon/lexicon/en/patterns/conditionals.tff
spacy_arguing_lexicon/lexicon/en/patterns/contrast.tff
spacy_arguing_lexicon/lexicon/en/patterns/difficulty.tff
spacy_arguing_lexicon/lexicon/en/patterns/doubt.tff
spacy_arguing_lexicon/lexicon/en/patterns/emphasis.tff
spacy_arguing_lexicon/lexicon/en/patterns/generalization.tff
spacy_arguing_lexicon/lexicon/en/patterns/inconsistency.tff
spacy_arguing_lexicon/lexicon/en/patterns/inyourshoes.tff
spacy_arguing_lexicon/lexicon/en/patterns/necessity.tff
spacy_arguing_lexicon/lexicon/en/patterns/possibility.tff
spacy_arguing_lexicon/lexicon/en/patterns/priority.tff
spacy_arguing_lexicon/lexicon/en/patterns/rhetoricalquestion.tff
spacy_arguing_lexicon/lexicon/en/patterns/structure.tff
spacy_arguing_lexicon/lexicon/en/patterns/wants.tff
spacy_arguing_lexicon/lexicon/nl/macros/intensifiers.tff
spacy_arguing_lexicon/lexicon/nl/macros/modals.tff
spacy_arguing_lexicon/lexicon/nl/macros/pronoun.tff
spacy_arguing_lexicon/lexicon/nl/macros/spoken.tff
spacy_arguing_lexicon/lexicon/nl/macros/wordclasses.tff
spacy_arguing_lexicon/lexicon/nl/patterns/assessments.tff
spacy_arguing_lexicon/lexicon/nl/patterns/authority.tff
spacy_arguing_lexicon/lexicon/nl/patterns/causation.tff
spacy_arguing_lexicon/lexicon/nl/patterns/conditionals.tff
spacy_arguing_lexicon/lexicon/nl/patterns/contrast.tff
spacy_arguing_lexicon-0.0.3.dist-info/METADATA
spacy_arguing_lexicon-0.0.3.dist-info/RECORD
spacy_arguing_lexicon-0.0.3.dist-info/WHEEL
spacy_arguing_lexicon-0.0.3.dist-info/top_level.txt
