Metadata-Version: 2.1
Name: spacy-arguing-lexicon
Version: 0.0.3
Summary: A spaCy extension wrapping around the arguing lexicon by MPQA
Home-page: https://github.com/fako/spacy_arguing_lexicon
Author: Fako Berkers
Author-email: email@fakoberkers.nl
License: UNKNOWN
Platform: UNKNOWN
Classifier: Programming Language :: Python :: 3
Classifier: License :: OSI Approved :: GNU General Public License v3 (GPLv3)
Classifier: Operating System :: OS Independent
Requires-Python: ~=3.4
Requires-Dist: spacy (>=2)
